[{"id":104009,"name":"Ånge","stateCode":"Y","countryCode":"SE"},{"id":104015,"name":"Ås","stateCode":"Y","countryCode":"SE"},{"id":103034,"name":"Bergeforsen","stateCode":"Y","countryCode":"SE"},{"id":103051,"name":"Bjästa","stateCode":"Y","countryCode":"SE"},{"id":103069,"name":"Bollstabruk","stateCode":"Y","countryCode":"SE"},{"id":103084,"name":"Bredbyn","stateCode":"Y","countryCode":"SE"},{"id":103185,"name":"Fränsta","stateCode":"Y","countryCode":"SE"},{"id":103322,"name":"Härnösand","stateCode":"Y","countryCode":"SE"},{"id":103311,"name":"Husum","stateCode":"Y","countryCode":"SE"},{"id":103352,"name":"Johannedal","stateCode":"Y","countryCode":"SE"},{"id":103445,"name":"Köpmanholmen","stateCode":"Y","countryCode":"SE"},{"id":103411,"name":"Kramfors","stateCode":"Y","countryCode":"SE"},{"id":103434,"name":"Kvissleby","stateCode":"Y","countryCode":"SE"},{"id":103502,"name":"Långsele","stateCode":"Y","countryCode":"SE"},{"id":103534,"name":"Matfors","stateCode":"Y","countryCode":"SE"},{"id":103574,"name":"Njurundabommen","stateCode":"Y","countryCode":"SE"},{"id":103575,"name":"Nolby","stateCode":"Y","countryCode":"SE"},{"id":104039,"name":"Örnsköldsvik","stateCode":"Y","countryCode":"SE"},{"id":103710,"name":"Skottsund","stateCode":"Y","countryCode":"SE"},{"id":103735,"name":"Sollefteå","stateCode":"Y","countryCode":"SE"},{"id":103833,"name":"Söråker","stateCode":"Y","countryCode":"SE"},{"id":103760,"name":"Stockvik","stateCode":"Y","countryCode":"SE"},{"id":103785,"name":"Sundsbruk","stateCode":"Y","countryCode":"SE"},{"id":103786,"name":"Sundsvall","stateCode":"Y","countryCode":"SE"},{"id":103850,"name":"Timrå","stateCode":"Y","countryCode":"SE"},{"id":103939,"name":"Vi","stateCode":"Y","countryCode":"SE"}]