[{"id":107262,"name":"Bahçesaray","stateCode":"65","countryCode":"TR"},{"id":107315,"name":"Başkale","stateCode":"65","countryCode":"TR"},{"id":108760,"name":"Çaldıran","stateCode":"65","countryCode":"TR"},{"id":108787,"name":"Çatak","stateCode":"65","countryCode":"TR"},{"id":107551,"name":"Edremit","stateCode":"65","countryCode":"TR"},{"id":107583,"name":"Erciş","stateCode":"65","countryCode":"TR"},{"id":107670,"name":"Gevaş","stateCode":"65","countryCode":"TR"},{"id":107753,"name":"Gürpınar","stateCode":"65","countryCode":"TR"},{"id":108908,"name":"İpekyolu","stateCode":"65","countryCode":"TR"},{"id":108220,"name":"Muradiye","stateCode":"65","countryCode":"TR"},{"id":108866,"name":"Özalp","stateCode":"65","countryCode":"TR"},{"id":108387,"name":"Saray","stateCode":"65","countryCode":"TR"},{"id":153361,"name":"Tuşba","stateCode":"65","countryCode":"TR"}]