[{"id":734,"name":"Bjelovar-Bilogora","countryId":55,"countryCode":"HR","countryName":"Croatia","stateCode":"07","type":"county","latitude":"45.89879720","longitude":"16.84230930"},{"id":737,"name":"Brod-Posavina","countryId":55,"countryCode":"HR","countryName":"Croatia","stateCode":"12","type":"county","latitude":"45.26379510","longitude":"17.32645620"},{"id":728,"name":"Dubrovnik-Neretva","countryId":55,"countryCode":"HR","countryName":"Croatia","stateCode":"19","type":"county","latitude":"43.07665880","longitude":"17.52684710"},{"id":743,"name":"Istria","countryId":55,"countryCode":"HR","countryName":"Croatia","stateCode":"18","type":"county","latitude":"45.12864550","longitude":"13.90154200"},{"id":5069,"name":"Karlovac","countryId":55,"countryCode":"HR","countryName":"Croatia","stateCode":"04","type":"county","latitude":"45.26133520","longitude":"15.52542016"},{"id":742,"name":"Koprivnica-Križevci","countryId":55,"countryCode":"HR","countryName":"Croatia","stateCode":"06","type":"county","latitude":"46.15689190","longitude":"16.83908260"},{"id":729,"name":"Krapina-Zagorje","countryId":55,"countryCode":"HR","countryName":"Croatia","stateCode":"02","type":"county","latitude":"46.10133930","longitude":"15.88096930"},{"id":731,"name":"Lika-Senj","countryId":55,"countryCode":"HR","countryName":"Croatia","stateCode":"09","type":"county","latitude":"44.61922180","longitude":"15.47016080"},{"id":726,"name":"Međimurje","countryId":55,"countryCode":"HR","countryName":"Croatia","stateCode":"20","type":"county","latitude":"46.37666440","longitude":"16.42132980"},{"id":740,"name":"Osijek-Baranja","countryId":55,"countryCode":"HR","countryName":"Croatia","stateCode":"14","type":"county","latitude":"45.55764280","longitude":"18.39421410"},{"id":724,"name":"Požega-Slavonia","countryId":55,"countryCode":"HR","countryName":"Croatia","stateCode":"11","type":"county","latitude":"45.34178680","longitude":"17.81143590"},{"id":735,"name":"Primorje-Gorski Kotar","countryId":55,"countryCode":"HR","countryName":"Croatia","stateCode":"08","type":"county","latitude":"45.31739960","longitude":"14.81674660"},{"id":730,"name":"Šibenik-Knin","countryId":55,"countryCode":"HR","countryName":"Croatia","stateCode":"15","type":"county","latitude":"43.92814850","longitude":"16.10376940"},{"id":733,"name":"Sisak-Moslavina","countryId":55,"countryCode":"HR","countryName":"Croatia","stateCode":"03","type":"county","latitude":"45.38379260","longitude":"16.53809940"},{"id":725,"name":"Split-Dalmatia","countryId":55,"countryCode":"HR","countryName":"Croatia","stateCode":"17","type":"county","latitude":"43.52403280","longitude":"16.81783770"},{"id":739,"name":"Varaždin","countryId":55,"countryCode":"HR","countryName":"Croatia","stateCode":"05","type":"county","latitude":"46.23174730","longitude":"16.33605590"},{"id":732,"name":"Virovitica-Podravina","countryId":55,"countryCode":"HR","countryName":"Croatia","stateCode":"10","type":"county","latitude":"45.65579850","longitude":"17.79324720"},{"id":741,"name":"Vukovar-Syrmia","countryId":55,"countryCode":"HR","countryName":"Croatia","stateCode":"16","type":"county","latitude":"45.17735520","longitude":"18.80535270"},{"id":727,"name":"Zadar","countryId":55,"countryCode":"HR","countryName":"Croatia","stateCode":"13","type":"county","latitude":"44.14693900","longitude":"15.61649430"},{"id":736,"name":"Zagreb","countryId":55,"countryCode":"HR","countryName":"Croatia","stateCode":"01","type":"county","latitude":"45.87066120","longitude":"16.39549100"},{"id":738,"name":"Zagreb","countryId":55,"countryCode":"HR","countryName":"Croatia","stateCode":"21","type":"city","latitude":"45.81501080","longitude":"15.98191890"}]