[{"id":80573,"name":"Bambamarca","stateCode":"CAJ","countryCode":"PE"},{"id":80575,"name":"Bellavista","stateCode":"CAJ","countryCode":"PE"},{"id":80580,"name":"Cajabamba","stateCode":"CAJ","countryCode":"PE"},{"id":80581,"name":"Cajamarca","stateCode":"CAJ","countryCode":"PE"},{"id":80600,"name":"Celendín","stateCode":"CAJ","countryCode":"PE"},{"id":80623,"name":"Chota","stateCode":"CAJ","countryCode":"PE"},{"id":80678,"name":"Jaén","stateCode":"CAJ","countryCode":"PE"},{"id":80785,"name":"Provincia de Cajabamba","stateCode":"CAJ","countryCode":"PE"},{"id":80786,"name":"Provincia de Cajamarca","stateCode":"CAJ","countryCode":"PE"},{"id":80802,"name":"Provincia de Celendín","stateCode":"CAJ","countryCode":"PE"},{"id":80806,"name":"Provincia de Chota","stateCode":"CAJ","countryCode":"PE"},{"id":80814,"name":"Provincia de Contumazá","stateCode":"CAJ","countryCode":"PE"},{"id":80819,"name":"Provincia de Cutervo","stateCode":"CAJ","countryCode":"PE"},{"id":80826,"name":"Provincia de Hualgayoc","stateCode":"CAJ","countryCode":"PE"},{"id":80847,"name":"Provincia de Jaén","stateCode":"CAJ","countryCode":"PE"},{"id":80886,"name":"Provincia de San Ignacio","stateCode":"CAJ","countryCode":"PE"},{"id":80888,"name":"Provincia de San Miguel","stateCode":"CAJ","countryCode":"PE"},{"id":80891,"name":"Provincia de Santa Cruz","stateCode":"CAJ","countryCode":"PE"},{"id":80944,"name":"San Ignacio","stateCode":"CAJ","countryCode":"PE"}]