[{"id":79770,"name":"Arrowtown","stateCode":"OTA","countryCode":"NZ"},{"id":79774,"name":"Balclutha","stateCode":"OTA","countryCode":"NZ"},{"id":79785,"name":"Clutha District","stateCode":"OTA","countryCode":"NZ"},{"id":79787,"name":"Cromwell","stateCode":"OTA","countryCode":"NZ"},{"id":79790,"name":"Dunedin","stateCode":"OTA","countryCode":"NZ"},{"id":79815,"name":"Kingston","stateCode":"OTA","countryCode":"NZ"},{"id":79830,"name":"Milton","stateCode":"OTA","countryCode":"NZ"},{"id":79844,"name":"Oamaru","stateCode":"OTA","countryCode":"NZ"},{"id":79855,"name":"Papatowai","stateCode":"OTA","countryCode":"NZ"},{"id":79863,"name":"Portobello","stateCode":"OTA","countryCode":"NZ"},{"id":79866,"name":"Queenstown","stateCode":"OTA","countryCode":"NZ"},{"id":79912,"name":"Wanaka","stateCode":"OTA","countryCode":"NZ"}]