[{"id":153377,"name":"Amdoun","stateId":2572,"stateCode":"31","stateName":"Béja","countryId":224,"countryCode":"TN","countryName":"Tunisia","latitude":"36.74420000","longitude":"9.05130000","wikiDataId":"Q1759415"},{"id":106930,"name":"Béja","stateId":2572,"stateCode":"31","stateName":"Béja","countryId":224,"countryCode":"TN","countryName":"Tunisia","latitude":"36.72564000","longitude":"9.18169000","wikiDataId":"Q177099"},{"id":106956,"name":"Goubellat","stateId":2572,"stateCode":"31","stateName":"Béja","countryId":224,"countryCode":"TN","countryName":"Tunisia","latitude":"36.59560000","longitude":"9.20780000","wikiDataId":"Q1759416"},{"id":106986,"name":"Medjez el Bab","stateId":2572,"stateCode":"31","stateName":"Béja","countryId":224,"countryCode":"TN","countryName":"Tunisia","latitude":"36.70640000","longitude":"9.61060000","wikiDataId":"Q267836"},{"id":106940,"name":"Nefza","stateId":2572,"stateCode":"31","stateName":"Béja","countryId":224,"countryCode":"TN","countryName":"Tunisia","latitude":"36.60490000","longitude":"8.97020000","wikiDataId":"Q2384004"},{"id":107031,"name":"Tabursuq","stateId":2572,"stateCode":"31","stateName":"Béja","countryId":224,"countryCode":"TN","countryName":"Tunisia","latitude":"36.45692000","longitude":"9.24751000","wikiDataId":"Q1890362"},{"id":153376,"name":"Téboursouk","stateId":2572,"stateCode":"31","stateName":"Béja","countryId":224,"countryCode":"TN","countryName":"Tunisia","latitude":"36.71040000","longitude":"9.00080000","wikiDataId":"Q1759693"},{"id":107035,"name":"Testour","stateId":2572,"stateCode":"31","stateName":"Béja","countryId":224,"countryCode":"TN","countryName":"Tunisia","latitude":"36.50140000","longitude":"9.66640000","wikiDataId":"Q398836"},{"id":153375,"name":"Thibar","stateId":2572,"stateCode":"31","stateName":"Béja","countryId":224,"countryCode":"TN","countryName":"Tunisia","latitude":"36.46560000","longitude":"9.06220000","wikiDataId":"Q555622"}]