[{"id":53426,"name":"Agua Blanca","stateId":3673,"stateCode":"JU","stateName":"Jutiapa Department","countryId":90,"countryCode":"GT","countryName":"Guatemala","latitude":"14.50000000","longitude":"-89.65000000","wikiDataId":"Q2403493"},{"id":53432,"name":"Asunción Mita","stateId":3673,"stateCode":"JU","stateName":"Jutiapa Department","countryId":90,"countryCode":"GT","countryName":"Guatemala","latitude":"14.33083000","longitude":"-89.71083000","wikiDataId":"Q2608750"},{"id":53433,"name":"Atescatempa","stateId":3673,"stateCode":"JU","stateName":"Jutiapa Department","countryId":90,"countryCode":"GT","countryName":"Guatemala","latitude":"14.17444000","longitude":"-89.74250000","wikiDataId":"Q2403627"},{"id":53466,"name":"Comapa","stateId":3673,"stateCode":"JU","stateName":"Jutiapa Department","countryId":90,"countryCode":"GT","countryName":"Guatemala","latitude":"14.11667000","longitude":"-89.91667000","wikiDataId":"Q2716888"},{"id":53473,"name":"Conguaco","stateId":3673,"stateCode":"JU","stateName":"Jutiapa Department","countryId":90,"countryCode":"GT","countryName":"Guatemala","latitude":"14.04417000","longitude":"-90.03111000","wikiDataId":"Q2403007"},{"id":53480,"name":"El Adelanto","stateId":3673,"stateCode":"JU","stateName":"Jutiapa Department","countryId":90,"countryCode":"GT","countryName":"Guatemala","latitude":"14.16667000","longitude":"-89.83333000","wikiDataId":"Q989812"},{"id":53486,"name":"El Progreso","stateId":3673,"stateCode":"JU","stateName":"Jutiapa Department","countryId":90,"countryCode":"GT","countryName":"Guatemala","latitude":"14.35000000","longitude":"-89.85000000","wikiDataId":"Q686756"},{"id":53511,"name":"Jalpatagua","stateId":3673,"stateCode":"JU","stateName":"Jutiapa Department","countryId":90,"countryCode":"GT","countryName":"Guatemala","latitude":"14.14167000","longitude":"-90.00861000","wikiDataId":"Q676590"},{"id":53512,"name":"Jerez","stateId":3673,"stateCode":"JU","stateName":"Jutiapa Department","countryId":90,"countryCode":"GT","countryName":"Guatemala","latitude":"14.10000000","longitude":"-89.75000000","wikiDataId":"Q1749094"},{"id":53516,"name":"Jutiapa","stateId":3673,"stateCode":"JU","stateName":"Jutiapa Department","countryId":90,"countryCode":"GT","countryName":"Guatemala","latitude":"14.29167000","longitude":"-89.89583000","wikiDataId":"Q2401953"},{"id":53539,"name":"Moyuta","stateId":3673,"stateCode":"JU","stateName":"Jutiapa Department","countryId":90,"countryCode":"GT","countryName":"Guatemala","latitude":"14.03861000","longitude":"-90.08083000","wikiDataId":"Q2403612"},{"id":53543,"name":"Municipio de Asunción Mita","stateId":3673,"stateCode":"JU","stateName":"Jutiapa Department","countryId":90,"countryCode":"GT","countryName":"Guatemala","latitude":"14.30330000","longitude":"-89.67623000","wikiDataId":"Q2403612"},{"id":53622,"name":"Pasaco","stateId":3673,"stateCode":"JU","stateName":"Jutiapa Department","countryId":90,"countryCode":"GT","countryName":"Guatemala","latitude":"13.97722000","longitude":"-90.20639000","wikiDataId":"Q371987"},{"id":53637,"name":"Quesada","stateId":3673,"stateCode":"JU","stateName":"Jutiapa Department","countryId":90,"countryCode":"GT","countryName":"Guatemala","latitude":"14.27028000","longitude":"-90.04028000","wikiDataId":"Q536249"},{"id":53682,"name":"San José Acatempa","stateId":3673,"stateCode":"JU","stateName":"Jutiapa Department","countryId":90,"countryCode":"GT","countryName":"Guatemala","latitude":"14.26528000","longitude":"-90.12694000","wikiDataId":"Q2403022"},{"id":53750,"name":"Santa Catarina Mita","stateId":3673,"stateCode":"JU","stateName":"Jutiapa Department","countryId":90,"countryCode":"GT","countryName":"Guatemala","latitude":"14.45000000","longitude":"-89.75000000","wikiDataId":"Q1748953"},{"id":53801,"name":"Yupiltepeque","stateId":3673,"stateCode":"JU","stateName":"Jutiapa Department","countryId":90,"countryCode":"GT","countryName":"Guatemala","latitude":"14.20000000","longitude":"-89.78333000","wikiDataId":"Q1749697"},{"id":53803,"name":"Zapotitlán","stateId":3673,"stateCode":"JU","stateName":"Jutiapa Department","countryId":90,"countryCode":"GT","countryName":"Guatemala","latitude":"14.13333000","longitude":"-89.83333000","wikiDataId":"Q2723903"}]