[{"id":55178,"name":"Ajka","stateCode":"VE","countryCode":"HU"},{"id":55179,"name":"Ajkai Járás","stateCode":"VE","countryCode":"HU"},{"id":55200,"name":"Badacsonytomaj","stateCode":"VE","countryCode":"HU"},{"id":55212,"name":"Balatonalmádi","stateCode":"VE","countryCode":"HU"},{"id":55213,"name":"Balatonalmádi Járás","stateCode":"VE","countryCode":"HU"},{"id":55218,"name":"Balatonfüred","stateCode":"VE","countryCode":"HU"},{"id":55219,"name":"Balatonfüredi Járás","stateCode":"VE","countryCode":"HU"},{"id":55220,"name":"Balatonkenese","stateCode":"VE","countryCode":"HU"},{"id":55241,"name":"Berhida","stateCode":"VE","countryCode":"HU"},{"id":55323,"name":"Csabrendek","stateCode":"VE","countryCode":"HU"},{"id":55335,"name":"Csetény","stateCode":"VE","countryCode":"HU"},{"id":55339,"name":"Csopak","stateCode":"VE","countryCode":"HU"},{"id":55360,"name":"Devecser","stateCode":"VE","countryCode":"HU"},{"id":55361,"name":"Devecseri Járás","stateCode":"VE","countryCode":"HU"},{"id":55492,"name":"Hajmáskér","stateCode":"VE","countryCode":"HU"},{"id":55506,"name":"Herend","stateCode":"VE","countryCode":"HU"},{"id":55664,"name":"Litér","stateCode":"VE","countryCode":"HU"},{"id":55766,"name":"Nemesvámos","stateCode":"VE","countryCode":"HU"},{"id":56172,"name":"Ősi","stateCode":"VE","countryCode":"HU"},{"id":55842,"name":"Pápa","stateCode":"VE","countryCode":"HU"},{"id":55843,"name":"Pápai Járás","stateCode":"VE","countryCode":"HU"},{"id":55858,"name":"Pétfürdő","stateCode":"VE","countryCode":"HU"},{"id":55879,"name":"Révfülöp","stateCode":"VE","countryCode":"HU"},{"id":55999,"name":"Sümeg","stateCode":"VE","countryCode":"HU"},{"id":56000,"name":"Sümegi Járás","stateCode":"VE","countryCode":"HU"},{"id":55943,"name":"Szentkirályszabadja","stateCode":"VE","countryCode":"HU"},{"id":56009,"name":"Tapolca","stateCode":"VE","countryCode":"HU"},{"id":56010,"name":"Tapolcai Járás","stateCode":"VE","countryCode":"HU"},{"id":56020,"name":"Tihany","stateCode":"VE","countryCode":"HU"},{"id":56166,"name":"Úrkút","stateCode":"VE","countryCode":"HU"},{"id":56112,"name":"Várpalota","stateCode":"VE","countryCode":"HU"},{"id":56113,"name":"Várpalotai Járás","stateCode":"VE","countryCode":"HU"},{"id":56100,"name":"Veszprém","stateCode":"VE","countryCode":"HU"},{"id":56101,"name":"Veszprémi Járás","stateCode":"VE","countryCode":"HU"},{"id":56138,"name":"Zánka","stateCode":"VE","countryCode":"HU"},{"id":56127,"name":"Zirc","stateCode":"VE","countryCode":"HU"},{"id":56128,"name":"Zirci Járás","stateCode":"VE","countryCode":"HU"}]